backend/credentials.py
backend/main.py
backend/run.py
cmbagent/Robot-MS-Aqua.png
cmbagent/Robot-MS-Grey.png
cmbagent/__init__.py
cmbagent/arxiv_downloader.py
cmbagent/base_agent.py
cmbagent/cli.py
cmbagent/cmbagent.py
cmbagent/context.py
cmbagent/data_retriever.py
cmbagent/functions.py
cmbagent/hand_offs.py
cmbagent/keywords_utils.py
cmbagent/literature.py
cmbagent/logo.png
cmbagent/ocr.py
cmbagent/output.py
cmbagent/rag_utils.py
cmbagent/structured_output.py
cmbagent/utils.py
cmbagent/version.py
cmbagent/vlm_injections.py
cmbagent/vlm_utils.py
cmbagent/agents/aaai_keywords_finder/__init__.py
cmbagent/agents/aaai_keywords_finder/aaai_keywords_finder.py
cmbagent/agents/aaai_keywords_finder/aaai_keywords_finder.yaml
cmbagent/agents/aas_keyword_finder/__init__.py
cmbagent/agents/aas_keyword_finder/aas_keyword_finder.py
cmbagent/agents/aas_keyword_finder/aas_keyword_finder.yaml
cmbagent/agents/admin/__init__.py
cmbagent/agents/admin/admin.py
cmbagent/agents/admin/admin.yaml
cmbagent/agents/camb_context/camb_context.py
cmbagent/agents/camb_context/camb_context.yaml
cmbagent/agents/camb_response_formatter/__init__.py
cmbagent/agents/camb_response_formatter/camb_response_formatter.py
cmbagent/agents/camb_response_formatter/camb_response_formatter.yaml
cmbagent/agents/classy_context/classy_context.py
cmbagent/agents/classy_context/classy_context.yaml
cmbagent/agents/classy_response_formatter/__init__.py
cmbagent/agents/classy_response_formatter/classy_response_formatter.py
cmbagent/agents/classy_response_formatter/classy_response_formatter.yaml
cmbagent/agents/classy_sz_response_formatter/__init__.py
cmbagent/agents/classy_sz_response_formatter/classy_sz_response_formatter.py
cmbagent/agents/classy_sz_response_formatter/classy_sz_response_formatter.yaml
cmbagent/agents/cobaya_response_formatter/__init__.py
cmbagent/agents/cobaya_response_formatter/cobaya_response_formatter.py
cmbagent/agents/cobaya_response_formatter/cobaya_response_formatter.yaml
cmbagent-0.0.1.post63.dist-info/licenses/LICENSE
cmbagent-0.0.1.post63.dist-info/METADATA
cmbagent-0.0.1.post63.dist-info/WHEEL
cmbagent-0.0.1.post63.dist-info/entry_points.txt
cmbagent-0.0.1.post63.dist-info/top_level.txt
cmbagent-0.0.1.post63.dist-info/RECORD
