Metadata-Version: 2.4
Name: cmbagent
Version: 0.0.1.post63
Summary: multi-agent system for autonomous discovery, made by cosmologists, powered by ag2
Maintainer-email: CMBAgents <boris.bolliet@cmbagent.community>
Project-URL: Homepage, https://github.com/CMBAgents/cmbagent
Project-URL: GitHub, https://github.com/CMBAgents/cmbagent
Requires-Python: >=3.12
License-File: LICENSE
Requires-Dist: anthropic
Requires-Dist: mistralai
Requires-Dist: ruamel.yaml
Requires-Dist: cmbagent_autogen>=0.0.91post11
Requires-Dist: jsonref==1.1.0
Requires-Dist: streamlit
Requires-Dist: ipython
Requires-Dist: fastapi>=0.104.1
Requires-Dist: uvicorn[standard]>=0.24.0
Requires-Dist: websockets>=12.0
Requires-Dist: python-multipart>=0.0.6
Requires-Dist: pydantic>=2.7.4
Requires-Dist: aiohttp>=3.9.0
Requires-Dist: camb>=1.6.0
Requires-Dist: cobaya
Requires-Dist: astropy>=6.0
Requires-Dist: healpy>=1.16
Requires-Dist: emcee>=3.1
Requires-Dist: numpy>=1.26
Requires-Dist: scipy>=1.12
Requires-Dist: pandas>=2.2
Requires-Dist: xarray>=2024.3
Requires-Dist: h5py>=3.10
Requires-Dist: matplotlib>=3.8
Requires-Dist: seaborn>=0.13
Requires-Dist: plotly>=5.21
Requires-Dist: scikit-learn>=1.4
Requires-Dist: statsmodels>=0.14
Requires-Dist: linearmodels>=5.1
Requires-Dist: yfinance>=0.2
Requires-Dist: xgboost>=2.0
Provides-Extra: jupyter
Requires-Dist: jupyterlab; extra == "jupyter"
Requires-Dist: jupyter-kernel-gateway; extra == "jupyter"
Requires-Dist: jupyter-client>=8.6.0; extra == "jupyter"
Requires-Dist: ipykernel>=6.29.0; extra == "jupyter"
Provides-Extra: nextjs
Dynamic: license-file
